{
  "kirby:DefaultCommonAttack": {
    "NAME": "Strike",
    "DESCRIPTION": "Deal !D! damage. NL [#0000ff]This[] [#ff0000]Is[] [#ffff00]How[] [#88888]color[] [#ff00ff]works.[]"
  },
  "kirby:DefaultCommonSkill": {
    "NAME": "Defend",
    "DESCRIPTION": "Gain !B! Block. NL kirby:Multiword_Keyword."
  },
  "kirby:DefaultCommonPower": {
    "NAME": "Hold Place",
    "DESCRIPTION": "Gain !M! kirby:Keyword.",
    "UPGRADE_DESCRIPTION": "Gain !M! kirby:Keywords."
  },
  "kirby:DefaultUncommonAttack": {
    "NAME": "Big slap",
    "DESCRIPTION": "Deal !D! damage."
  },
  "kirby:DefaultUncommonSkill": {
    "NAME": "A Better Defend",
    "DESCRIPTION": "Gain !B! Plated Armor. Affected by Dexterity."
  },
  "kirby:DefaultUncommonPower": {
    "NAME": "Weirdness",
    "DESCRIPTION": "Gain X kirby:Keywords.",
    "UPGRADE_DESCRIPTION": "Gain X +1 kirby:Keywords."
  },
  "kirby:DefaultRareAttack": {
    "NAME": "TOUCH",
    "DESCRIPTION": "Deal !D! damage."
  },
  "kirby:DefaultRareSkill": {
    "NAME": "For Each Loop x2",
    "DESCRIPTION": "Apply !M! Vulnerable to all enemies, 2 times.",
    "UPGRADE_DESCRIPTION": "Apply !M! Vulnerable to all enemies, 3 times."
  },
  "kirby:DefaultRarePower": {
    "NAME": "In-Progress Form",
    "DESCRIPTION": "At the start of your turn, play a TOUCH."
  },
  "kirby:DefaultAttackWithVariable": {
    "NAME": "Special Strike",
    "DESCRIPTION": "Deal !D! damage [E] times. NL (Deal !kirby:ENERGY_DAMAGE! damage total.)"
  },
  "kirby:DefaultSecondMagicNumberSkill": {
    "NAME": "Cool 2 Number Card",
    "DESCRIPTION": "Apply !M! Vulnerable and !kirby:SecondMagic! poison to an enemy."
  },
  "kirby:OrbSkill": {
    "NAME": "Get Orb",
    "DESCRIPTION": "Channel 1 Default Orb."
  },
  "kirby:Inhale": {
    "NAME": "Inhale",
    "DESCRIPTION": "kirby:Inhale an enemy below or equal to !M! HP.",
    "EXTENDED_DESCRIPTION": [
      "This enemy has too much HP."
    ]
  }
}
